<?xml version="1.0" encoding="utf-8"?>
<ArrayOfOrder xmlns:xsi="http://www.w3.org/2001/XMLSchema-instance" xmlns:xsd="http://www.w3.org/2001/XMLSchema">
  <Order>
    <ID>500000</ID>
    <CustomerName>bbb</CustomerName>
    <CustomerEmail>iii</CustomerEmail>
    <CustomerAddress>ddd</CustomerAddress>
    <OrderDate>2020-09-18T00:00:00</OrderDate>
    <ShipDate>2020-09-23T00:00:00</ShipDate>
    <DeliveryDate>2023-02-16T19:11:03.6033226+02:00</DeliveryDate>
  </Order>
  <Order>
    <ID>500001</ID>
    <CustomerName>aaa</CustomerName>
    <CustomerEmail>iii</CustomerEmail>
    <CustomerAddress>fff</CustomerAddress>
    <OrderDate>2014-07-26T00:00:00</OrderDate>
    <ShipDate>2014-07-31T00:00:00</ShipDate>
    <DeliveryDate>2014-08-30T00:00:00</DeliveryDate>
  </Order>
  <Order>
    <ID>500002</ID>
    <CustomerName>aaa</CustomerName>
    <CustomerEmail>hhh</CustomerEmail>
    <CustomerAddress>fff</CustomerAddress>
    <OrderDate>2010-09-27T00:00:00</OrderDate>
    <ShipDate>2010-10-02T00:00:00</ShipDate>
    <DeliveryDate>2010-11-01T00:00:00</DeliveryDate>
  </Order>
  <Order>
    <ID>500003</ID>
    <CustomerName>bbb</CustomerName>
    <CustomerEmail>iii</CustomerEmail>
    <CustomerAddress>eee</CustomerAddress>
    <OrderDate>2011-11-06T00:00:00</OrderDate>
    <ShipDate>2011-11-11T00:00:00</ShipDate>
    <DeliveryDate>2011-12-11T00:00:00</DeliveryDate>
  </Order>
  <Order>
    <ID>500004</ID>
    <CustomerName>bbb</CustomerName>
    <CustomerEmail>ggg</CustomerEmail>
    <CustomerAddress>ddd</CustomerAddress>
    <OrderDate>2015-10-10T00:00:00</OrderDate>
    <ShipDate>2015-10-15T00:00:00</ShipDate>
    <DeliveryDate>2015-11-14T00:00:00</DeliveryDate>
  </Order>
  <Order>
    <ID>500005</ID>
    <CustomerName>bbb</CustomerName>
    <CustomerEmail>iii</CustomerEmail>
    <CustomerAddress>ddd</CustomerAddress>
    <OrderDate>2022-10-23T00:00:00</OrderDate>
    <ShipDate>2023-02-16T19:12:00.7209654+02:00</ShipDate>
    <DeliveryDate>2023-02-16T19:14:33.0242434+02:00</DeliveryDate>
  </Order>
  <Order>
    <ID>500006</ID>
    <CustomerName>aaa</CustomerName>
    <CustomerEmail>iii</CustomerEmail>
    <CustomerAddress>ddd</CustomerAddress>
    <OrderDate>2020-03-17T00:00:00</OrderDate>
    <ShipDate>2020-03-22T00:00:00</ShipDate>
    <DeliveryDate>2023-02-16T19:16:16.2573057+02:00</DeliveryDate>
  </Order>
  <Order>
    <ID>500007</ID>
    <CustomerName>bbb</CustomerName>
    <CustomerEmail>iii</CustomerEmail>
    <CustomerAddress>ddd</CustomerAddress>
    <OrderDate>2012-09-13T00:00:00</OrderDate>
    <ShipDate>2012-09-18T00:00:00</ShipDate>
    <DeliveryDate>2012-10-18T00:00:00</DeliveryDate>
  </Order>
  <Order>
    <ID>500008</ID>
    <CustomerName>bbb</CustomerName>
    <CustomerEmail>ggg</CustomerEmail>
    <CustomerAddress>eee</CustomerAddress>
    <OrderDate>2019-02-07T00:00:00</OrderDate>
    <ShipDate>2023-02-16T19:22:31.5548703+02:00</ShipDate>
    <DeliveryDate>2023-02-16T19:22:37.9247853+02:00</DeliveryDate>
  </Order>
  <Order>
    <ID>500009</ID>
    <CustomerName>aaa</CustomerName>
    <CustomerEmail>iii</CustomerEmail>
    <CustomerAddress>eee</CustomerAddress>
    <OrderDate>2010-05-10T00:00:00</OrderDate>
    <ShipDate>2010-05-15T00:00:00</ShipDate>
    <DeliveryDate>2010-06-14T00:00:00</DeliveryDate>
  </Order>
  <Order>
    <ID>500010</ID>
    <CustomerName>bbb</CustomerName>
    <CustomerEmail>iii</CustomerEmail>
    <CustomerAddress>fff</CustomerAddress>
    <OrderDate>2021-03-01T00:00:00</OrderDate>
    <ShipDate>2021-03-06T00:00:00</ShipDate>
    <DeliveryDate>2023-02-16T19:25:53.7091891+02:00</DeliveryDate>
  </Order>
  <Order>
    <ID>500011</ID>
    <CustomerName>aaa</CustomerName>
    <CustomerEmail>iii</CustomerEmail>
    <CustomerAddress>fff</CustomerAddress>
    <OrderDate>2021-12-03T00:00:00</OrderDate>
    <ShipDate xsi:nil="true" />
    <DeliveryDate xsi:nil="true" />
  </Order>
  <Order>
    <ID>500012</ID>
    <CustomerName>ccc</CustomerName>
    <CustomerEmail>ggg</CustomerEmail>
    <CustomerAddress>eee</CustomerAddress>
    <OrderDate>2020-07-22T00:00:00</OrderDate>
    <ShipDate xsi:nil="true" />
    <DeliveryDate xsi:nil="true" />
  </Order>
  <Order>
    <ID>500013</ID>
    <CustomerName>ccc</CustomerName>
    <CustomerEmail>hhh</CustomerEmail>
    <CustomerAddress>eee</CustomerAddress>
    <OrderDate>2014-01-21T00:00:00</OrderDate>
    <ShipDate>2014-01-26T00:00:00</ShipDate>
    <DeliveryDate>2014-02-25T00:00:00</DeliveryDate>
  </Order>
  <Order>
    <ID>500014</ID>
    <CustomerName>ccc</CustomerName>
    <CustomerEmail>hhh</CustomerEmail>
    <CustomerAddress>fff</CustomerAddress>
    <OrderDate>2021-04-05T00:00:00</OrderDate>
    <ShipDate>2021-04-10T00:00:00</ShipDate>
    <DeliveryDate>2021-05-10T00:00:00</DeliveryDate>
  </Order>
  <Order>
    <ID>500015</ID>
    <CustomerName>ccc</CustomerName>
    <CustomerEmail>iii</CustomerEmail>
    <CustomerAddress>ddd</CustomerAddress>
    <OrderDate>2016-03-07T00:00:00</OrderDate>
    <ShipDate>2016-03-12T00:00:00</ShipDate>
    <DeliveryDate>2016-04-11T00:00:00</DeliveryDate>
  </Order>
  <Order>
    <ID>500016</ID>
    <CustomerName>ccc</CustomerName>
    <CustomerEmail>ggg</CustomerEmail>
    <CustomerAddress>fff</CustomerAddress>
    <OrderDate>2021-08-29T00:00:00</OrderDate>
    <ShipDate>2021-09-03T00:00:00</ShipDate>
    <DeliveryDate>2023-02-16T18:51:05.3086596+02:00</DeliveryDate>
  </Order>
  <Order>
    <ID>500017</ID>
    <CustomerName>bbb</CustomerName>
    <CustomerEmail>ggg</CustomerEmail>
    <CustomerAddress>eee</CustomerAddress>
    <OrderDate>2014-05-06T00:00:00</OrderDate>
    <ShipDate xsi:nil="true" />
    <DeliveryDate xsi:nil="true" />
  </Order>
  <Order>
    <ID>500018</ID>
    <CustomerName>aaa</CustomerName>
    <CustomerEmail>hhh</CustomerEmail>
    <CustomerAddress>fff</CustomerAddress>
    <OrderDate>2010-11-01T00:00:00</OrderDate>
    <ShipDate>2010-11-06T00:00:00</ShipDate>
    <DeliveryDate>2010-12-06T00:00:00</DeliveryDate>
  </Order>
  <Order>
    <ID>500019</ID>
    <CustomerName>ccc</CustomerName>
    <CustomerEmail>iii</CustomerEmail>
    <CustomerAddress>fff</CustomerAddress>
    <OrderDate>2022-07-08T00:00:00</OrderDate>
    <ShipDate>2022-07-13T00:00:00</ShipDate>
    <DeliveryDate>2022-08-12T00:00:00</DeliveryDate>
  </Order>
  <Order>
    <CustomerName>yuyuyu</CustomerName>
    <CustomerEmail>yu@gma.mo.il</CustomerEmail>
    <CustomerAddress>ghj</CustomerAddress>
    <ID>500034</ID>
    <OrderDate>2023-02-16T19:22:11.4185356+02:00</OrderDate>
    <ShipDate />
    <DeliveryDate />
  </Order>
</ArrayOfOrder>